metal/__init__.py
metal/analysis.py
metal/classifier.py
metal/metrics.py
metal/utils.py
metal/contrib/__init__.py
metal/contrib/backends/__init__.py
metal/contrib/backends/wrapper.py
metal/contrib/featurizers/__init__.py
metal/contrib/featurizers/embedding_featurizer.py
metal/contrib/featurizers/featurizer.py
metal/contrib/featurizers/ngram_featurizer.py
metal/contrib/info_extraction/__init__.py
metal/contrib/info_extraction/mentions.py
metal/contrib/info_extraction/utils.py
metal/contrib/modules/__init__.py
metal/contrib/modules/lstm_module.py
metal/contrib/modules/resnet_cifar10.py
metal/contrib/modules/sparse_linear_module.py
metal/contrib/visualization/__init__.py
metal/contrib/visualization/analysis.py
metal/end_model/__init__.py
metal/end_model/em_defaults.py
metal/end_model/end_model.py
metal/end_model/identity_module.py
metal/end_model/logreg.py
metal/end_model/loss.py
metal/label_model/__init__.py
metal/label_model/baselines.py
metal/label_model/class_balance.py
metal/label_model/graph_utils.py
metal/label_model/label_model.py
metal/label_model/lm_defaults.py
metal/label_model/utils.py
metal/logging/__init__.py
metal/logging/checkpointer.py
metal/logging/logger.py
metal/logging/tensorboard.py
metal/logging/utils.py
metal/logging/writer.py
metal/mmtl/__init__.py
metal/mmtl/data.py
metal/mmtl/metal_model.py
metal/mmtl/mmtl_logger.py
metal/mmtl/modules.py
metal/mmtl/payload.py
metal/mmtl/scorer.py
metal/mmtl/task.py
metal/mmtl/task_scheduler.py
metal/mmtl/token_task.py
metal/mmtl/trainer.py
metal/multitask/__init__.py
metal/multitask/mt_classifier.py
metal/multitask/mt_em_defaults.py
metal/multitask/mt_end_model.py
metal/multitask/mt_label_model.py
metal/multitask/task_graph.py
metal/multitask/utils.py
metal/tuners/__init__.py
metal/tuners/hyperband_tuner.py
metal/tuners/random_tuner.py
metal/tuners/tuner.py
synthetic/__init__.py
synthetic/generate.py
synthetic/words1k.py
tests/__init__.py
tests/metal/__init__.py
tests/metal/test_analysis.py
snorkel_metal-0.5.0.dist-info/LICENSE
snorkel_metal-0.5.0.dist-info/METADATA
snorkel_metal-0.5.0.dist-info/WHEEL
snorkel_metal-0.5.0.dist-info/top_level.txt
snorkel_metal-0.5.0.dist-info/RECORD
