Metadata-Version: 2.1
Name: snorkel-metal
Version: 0.5.0
Summary: A system for quickly generating training data with multi-task weak supervision
Home-page: https://github.com/HazyResearch/metal
License: Apache License 2.0
Project-URL: Homepage, https://hazyresearch.github.io/snorkel/
Project-URL: Source, https://github.com/HazyResearch/metal/
Project-URL: Bug Reports, https://github.com/HazyResearch/metal/issues
Project-URL: Citation, https://arxiv.org/abs/1810.02840
Keywords: machine-learning ai information-extraction weak-supervision mtl multitask multi-task-learning
Platform: UNKNOWN
Classifier: Intended Audience :: Science/Research
Classifier: Topic :: Scientific/Engineering :: Information Analysis
Classifier: License :: OSI Approved :: Apache Software License
Classifier: Programming Language :: Python :: 3
Classifier: Programming Language :: Python :: 3.6
Classifier: Programming Language :: Python :: 3.7
Requires-Python: >=3.6
Requires-Dist: dill
Requires-Dist: networkx (>=2.2)
Requires-Dist: numpy
Requires-Dist: pandas
Requires-Dist: torch (>=1.0)
Requires-Dist: scipy
Requires-Dist: tqdm
Requires-Dist: scikit-learn
